LICENSE
MANIFEST.in
README.md
pyproject.toml
requirements.txt
setup.cfg
setup.py
diffusersplus/__init__.py
diffusersplus/automodel.py
diffusersplus/demo.py
diffusersplus/preprocces.py
diffusersplus.egg-info/PKG-INFO
diffusersplus.egg-info/SOURCES.txt
diffusersplus.egg-info/dependency_links.txt
diffusersplus.egg-info/requires.txt
diffusersplus.egg-info/top_level.txt
diffusersplus/pipelines/__init__.py
diffusersplus/pipelines/base.py
diffusersplus/pipelines/controlnet.py
diffusersplus/pipelines/controlnet_img2img.py
diffusersplus/pipelines/controlnet_inpaint.py
diffusersplus/pipelines/stable_img2img.py
diffusersplus/pipelines/stable_txt2img.py
diffusersplus/pipelines/stable_upscale.py
diffusersplus/utils/__init__.py
diffusersplus/utils/data_utils.py
diffusersplus/utils/downloads.py
diffusersplus/utils/model_list.py
diffusersplus/utils/scheduler_utils.py
diffusersplus/utils/video_utils.py